ipycobe/__init__.py
ipycobe/static/widget.css
ipycobe/static/widget.js
ipycobe-0.1.1.dist-info/METADATA
ipycobe-0.1.1.dist-info/WHEEL
ipycobe-0.1.1.dist-info/RECORD
