Metadata-Version: 2.4
Name: ipycobe
Version: 0.1.1
Requires-Python: >=3.11
Requires-Dist: anywidget
Provides-Extra: dev
Requires-Dist: jupyterlab; extra == 'dev'
Requires-Dist: ruff; extra == 'dev'
Requires-Dist: watchfiles; extra == 'dev'
